django_otp_keygen/__init__.py
django_otp_keygen/abstract_model.py
django_otp_keygen/admin.py
django_otp_keygen/constants.py
django_otp_keygen/otp.py
django_otp_keygen/otp_service.py
django_otp_keygen/utils.py
django_otp_keygen-0.1.1.dist-info/licenses/AUTHORS.rst
django_otp_keygen-0.1.1.dist-info/licenses/LICENCE
django_otp_keygen-0.1.1.dist-info/METADATA
django_otp_keygen-0.1.1.dist-info/WHEEL
django_otp_keygen-0.1.1.dist-info/top_level.txt
django_otp_keygen-0.1.1.dist-info/RECORD
