Metadata-Version: 2.4
Name: django-otp-keygen
Version: 0.1.1
Summary: Django OTP key generator and validator
Home-page: https://github.com/yourusername/django-otp-keygen
Author: Mohit Prajapat
Author-email: Mohit Prajapat <mohitdevelopment2001@gmail.com>
Project-URL: Homepage, https://github.com/mohitprajapat2001/django-otp-keygen
Project-URL: Documentation, https://github.com/mohitprajapat2001/django-otp-keygen/wiki
Requires-Python: >=3.10
License-File: LICENCE
License-File: AUTHORS.rst
Requires-Dist: Django>=5.0
Dynamic: license-file
